[
  {
    "Date Pulled": "2017-03-24",
    "name": "Adam Cracknell",
    "points": "3",
    "team": "DAL",
    "toi": "11:35"
  },
  {
    "Date Pulled": "2017-03-24",
    "name": "Jason Spezza",
    "points": "3",
    "team": "DAL",
    "toi": "12:06"
  },
  {
    "Date Pulled": "2017-03-24",
    "name": "Jakob Silfverberg",
    "points": "2",
    "team": "ANA",
    "toi": "17:55"
  },
  {
    "Date Pulled": "2017-03-24",
    "name": "Matt Cullen",
    "points": "2",
    "team": "PIT",
    "toi": "18:28"
  },
  {
    "Date Pulled": "2017-03-24",
    "name": "Cameron Gaunce",
    "points": "2",
    "team": "PIT",
    "toi": "15:53"
  },
  {
    "Date Pulled": "2017-03-24",
    "name": "Nikita Kucherov",
    "points": "2",
    "team": "TBL",
    "toi": "22:05"
  },
  {
    "Date Pulled": "2017-03-24",
    "name": "Remi Elie",
    "points": "2",
    "team": "DAL",
    "toi": "15:01"
  },
  {
    "Date Pulled": "2017-03-24",
    "name": "Curtis McKenzie",
    "points": "2",
    "team": "DAL",
    "toi": "12:47"
  },
  {
    "Date Pulled": "2017-03-24",
    "name": "John Tavares",
    "points": "2",
    "team": "NYI",
    "toi": "21:20"
  },
  {
    "Date Pulled": "2017-03-24",
    "name": "Phil Kessel",
    "points": "2",
    "team": "PIT",
    "toi": "19:55"
  },
  {
    "Date Pulled": "2017-03-24",
    "name": "Andrew Cogliano",
    "points": "1",
    "team": "ANA",
    "toi": "17:15"
  },
  {
    "Date Pulled": "2017-03-24",
    "name": "John Klingberg",
    "points": "1",
    "team": "DAL",
    "toi": "18:45"
  },
  {
    "Date Pulled": "2017-03-24",
    "name": "Jamie Benn",
    "points": "1",
    "team": "DAL",
    "toi": "16:35"
  },
  {
    "Date Pulled": "2017-03-24",
    "name": "Sidney Crosby",
    "points": "1",
    "team": "PIT",
    "toi": "20:29"
  },
  {
    "Date Pulled": "2017-03-24",
    "name": "Anders Lee",
    "points": "1",
    "team": "NYI",
    "toi": "16:36"
  },
  {
    "Date Pulled": "2017-03-24",
    "name": "Corey Perry",
    "points": "1",
    "team": "ANA",
    "toi": "16:42"
  },
  {
    "Date Pulled": "2017-03-24",
    "name": "Brett Ritchie",
    "points": "1",
    "team": "DAL",
    "toi": "15:48"
  },
  {
    "Date Pulled": "2017-03-24",
    "name": "Brock Nelson",
    "points": "1",
    "team": "NYI",
    "toi": "17:25"
  },
  {
    "Date Pulled": "2017-03-24",
    "name": "Ondrej Palat",
    "points": "1",
    "team": "TBL",
    "toi": "23:30"
  },
  {
    "Date Pulled": "2017-03-24",
    "name": "Henrik Zetterberg",
    "points": "1",
    "team": "DET",
    "toi": "22:15"
  },
  {
    "Date Pulled": "2017-03-24",
    "name": "Casey Cizikas",
    "points": "1",
    "team": "NYI",
    "toi": "15:00"
  },
  {
    "Date Pulled": "2017-03-24",
    "name": "Joe Thornton",
    "points": "1",
    "team": "SJS",
    "toi": "13:46"
  },
  {
    "Date Pulled": "2017-03-24",
    "name": "Josh Morrissey",
    "points": "1",
    "team": "WPG",
    "toi": "20:53"
  },
  {
    "Date Pulled": "2017-03-24",
    "name": "Cam Fowler",
    "points": "1",
    "team": "ANA",
    "toi": "26:49"
  },
  {
    "Date Pulled": "2017-03-24",
    "name": "Brandon Montour",
    "points": "1",
    "team": "ANA",
    "toi": "14:16"
  },
  {
    "Date Pulled": "2017-03-24",
    "name": "Tyler Seguin",
    "points": "1",
    "team": "DAL",
    "toi": "15:00"
  },
  {
    "Date Pulled": "2017-03-24",
    "name": "Braydon Coburn",
    "points": "1",
    "team": "TBL",
    "toi": "19:53"
  },
  {
    "Date Pulled": "2017-03-24",
    "name": "Cody Eakin",
    "points": "1",
    "team": "DAL",
    "toi": "17:55"
  },
  {
    "Date Pulled": "2017-03-24",
    "name": "Ales Hemsky",
    "points": "1",
    "team": "DAL",
    "toi": "15:12"
  },
  {
    "Date Pulled": "2017-03-24",
    "name": "Joshua Ho-Sang",
    "points": "1",
    "team": "NYI",
    "toi": "17:21"
  },
  {
    "Date Pulled": "2017-03-24",
    "name": "Ryan Kesler",
    "points": "1",
    "team": "ANA",
    "toi": "20:53"
  },
  {
    "Date Pulled": "2017-03-24",
    "name": "Gustav Nyquist",
    "points": "1",
    "team": "DET",
    "toi": "19:16"
  },
  {
    "Date Pulled": "2017-03-24",
    "name": "Brayden Point",
    "points": "1",
    "team": "TBL",
    "toi": "23:28"
  },
  {
    "Date Pulled": "2017-03-24",
    "name": "Alan Quine",
    "points": "1",
    "team": "NYI",
    "toi": "11:54"
  },
  {
    "Date Pulled": "2017-03-24",
    "name": "Nick Ritchie",
    "points": "1",
    "team": "ANA",
    "toi": "11:08"
  },
  {
    "Date Pulled": "2017-03-24",
    "name": "Chad Ruhwedel",
    "points": "1",
    "team": "PIT",
    "toi": "20:39"
  },
  {
    "Date Pulled": "2017-03-24",
    "name": "Conor Sheary",
    "points": "1",
    "team": "PIT",
    "toi": "19:31"
  },
  {
    "Date Pulled": "2017-03-24",
    "name": "Josh Bailey",
    "points": "1",
    "team": "NYI",
    "toi": "19:16"
  },
  {
    "Date Pulled": "2017-03-24",
    "name": "Frans Nielsen",
    "points": "1",
    "team": "DET",
    "toi": "19:46"
  },
  {
    "Date Pulled": "2017-03-24",
    "name": "Mathieu Perreault",
    "points": "1",
    "team": "WPG",
    "toi": "18:37"
  },
  {
    "Date Pulled": "2017-03-24",
    "name": "Blake Wheeler",
    "points": "1",
    "team": "WPG",
    "toi": "20:57"
  },
  {
    "Date Pulled": "2017-03-24",
    "name": "Brent Burns",
    "points": "1",
    "team": "SJS",
    "toi": "22:56"
  },
  {
    "Date Pulled": "2017-03-24",
    "name": "Esa Lindell",
    "points": "0",
    "team": "DAL",
    "toi": "19:14"
  },
  {
    "Date Pulled": "2017-03-24",
    "name": "Greg Pateryn",
    "points": "0",
    "team": "DAL",
    "toi": "19:54"
  },
  {
    "Date Pulled": "2017-03-24",
    "name": "Jamie Oleksiak",
    "points": "0",
    "team": "DAL",
    "toi": "21:20"
  },
  {
    "Date Pulled": "2017-03-24",
    "name": "Jake Dotchin",
    "points": "0",
    "team": "TBL",
    "toi": "19:58"
  },
  {
    "Date Pulled": "2017-03-24",
    "name": "Ryan Getzlaf",
    "points": "0",
    "team": "ANA",
    "toi": "20:24"
  },
  {
    "Date Pulled": "2017-03-24",
    "name": "Travis Hamonic",
    "points": "0",
    "team": "NYI",
    "toi": "24:08"
  },
  {
    "Date Pulled": "2017-03-24",
    "name": "Stephen Johns",
    "points": "0",
    "team": "DAL",
    "toi": "19:12"
  },
  {
    "Date Pulled": "2017-03-24",
    "name": "Josh Manson",
    "points": "0",
    "team": "ANA",
    "toi": "19:45"
  },
  {
    "Date Pulled": "2017-03-24",
    "name": "Patrik Nemeth",
    "points": "0",
    "team": "DAL",
    "toi": "18:53"
  },
  {
    "Date Pulled": "2017-03-24",
    "name": "Tomas Nosek",
    "points": "0",
    "team": "DET",
    "toi": "9:03"
  },
  {
    "Date Pulled": "2017-03-24",
    "name": "Carter Rowney",
    "points": "0",
    "team": "PIT",
    "toi": "16:03"
  },
  {
    "Date Pulled": "2017-03-24",
    "name": "Bryan Rust",
    "points": "0",
    "team": "PIT",
    "toi": "16:19"
  },
  {
    "Date Pulled": "2017-03-24",
    "name": "Antoine Vermette",
    "points": "0",
    "team": "ANA",
    "toi": "14:35"
  },
  {
    "Date Pulled": "2017-03-24",
    "name": "Justin Abdelkader",
    "points": "0",
    "team": "DET",
    "toi": "15:50"
  },
  {
    "Date Pulled": "2017-03-24",
    "name": "Josh Archibald",
    "points": "0",
    "team": "PIT",
    "toi": "8:21"
  },
  {
    "Date Pulled": "2017-03-24",
    "name": "Jared Boll",
    "points": "0",
    "team": "ANA",
    "toi": "6:53"
  },
  {
    "Date Pulled": "2017-03-24",
    "name": "Justin Braun",
    "points": "0",
    "team": "SJS",
    "toi": "21:16"
  },
  {
    "Date Pulled": "2017-03-24",
    "name": "J.T. Brown",
    "points": "0",
    "team": "TBL",
    "toi": "7:42"
  },
  {
    "Date Pulled": "2017-03-24",
    "name": "Jason Chimera",
    "points": "0",
    "team": "NYI",
    "toi": "15:35"
  },
  {
    "Date Pulled": "2017-03-24",
    "name": "Ian Cole",
    "points": "0",
    "team": "PIT",
    "toi": "19:44"
  },
  {
    "Date Pulled": "2017-03-24",
    "name": "Logan Couture",
    "points": "0",
    "team": "SJS",
    "toi": "16:10"
  },
  {
    "Date Pulled": "2017-03-24",
    "name": "Calvin de Haan",
    "points": "0",
    "team": "NYI",
    "toi": "22:54"
  },
  {
    "Date Pulled": "2017-03-24",
    "name": "Danny DeKeyser",
    "points": "0",
    "team": "DET",
    "toi": "20:14"
  },
  {
    "Date Pulled": "2017-03-24",
    "name": "Jonathan Drouin",
    "points": "0",
    "team": "TBL",
    "toi": "19:20"
  },
  {
    "Date Pulled": "2017-03-24",
    "name": "Gabriel Dumont",
    "points": "0",
    "team": "TBL",
    "toi": "7:15"
  },
  {
    "Date Pulled": "2017-03-24",
    "name": "Patrick Eaves",
    "points": "0",
    "team": "ANA",
    "toi": "15:50"
  },
  {
    "Date Pulled": "2017-03-24",
    "name": "Nikolaj Ehlers",
    "points": "0",
    "team": "WPG",
    "toi": "17:01"
  },
  {
    "Date Pulled": "2017-03-24",
    "name": "Adam Erne",
    "points": "0",
    "team": "TBL",
    "toi": "8:15"
  },
  {
    "Date Pulled": "2017-03-24",
    "name": "Radek Faksa",
    "points": "0",
    "team": "DAL",
    "toi": "16:48"
  },
  {
    "Date Pulled": "2017-03-24",
    "name": "Luke Glendening",
    "points": "0",
    "team": "DET",
    "toi": "14:15"
  },
  {
    "Date Pulled": "2017-03-24",
    "name": "Yanni Gourde",
    "points": "0",
    "team": "TBL",
    "toi": "16:51"
  },
  {
    "Date Pulled": "2017-03-24",
    "name": "Victor Hedman",
    "points": "0",
    "team": "TBL",
    "toi": "26:58"
  },
  {
    "Date Pulled": "2017-03-24",
    "name": "Korbinian Holzer",
    "points": "0",
    "team": "ANA",
    "toi": "9:23"
  },
  {
    "Date Pulled": "2017-03-24",
    "name": "Nick Jensen",
    "points": "0",
    "team": "DET",
    "toi": "20:41"
  },
  {
    "Date Pulled": "2017-03-24",
    "name": "Alex Killorn",
    "points": "0",
    "team": "TBL",
    "toi": "21:05"
  },
  {
    "Date Pulled": "2017-03-24",
    "name": "Niklas Kronwall",
    "points": "0",
    "team": "DET",
    "toi": "20:02"
  },
  {
    "Date Pulled": "2017-03-24",
    "name": "Tom Kuhnhackl",
    "points": "0",
    "team": "PIT",
    "toi": "8:57"
  },
  {
    "Date Pulled": "2017-03-24",
    "name": "Nikolai Kulemin",
    "points": "0",
    "team": "NYI",
    "toi": "4:42"
  },
  {
    "Date Pulled": "2017-03-24",
    "name": "Patrik Laine",
    "points": "0",
    "team": "WPG",
    "toi": "16:07"
  },
  {
    "Date Pulled": "2017-03-24",
    "name": "Dylan Larkin",
    "points": "0",
    "team": "DET",
    "toi": "16:08"
  },
  {
    "Date Pulled": "2017-03-24",
    "name": "Nick Leddy",
    "points": "0",
    "team": "NYI",
    "toi": "24:28"
  },
  {
    "Date Pulled": "2017-03-24",
    "name": "Hampus Lindholm",
    "points": "0",
    "team": "ANA",
    "toi": "24:10"
  },
  {
    "Date Pulled": "2017-03-24",
    "name": "Scott Mayfield",
    "points": "0",
    "team": "NYI",
    "toi": "16:01"
  },
  {
    "Date Pulled": "2017-03-24",
    "name": "Greg McKegg",
    "points": "0",
    "team": "TBL",
    "toi": "3:28"
  },
  {
    "Date Pulled": "2017-03-24",
    "name": "Drew Miller",
    "points": "0",
    "team": "DET",
    "toi": "13:25"
  },
  {
    "Date Pulled": "2017-03-24",
    "name": "Vladislav Namestnikov",
    "points": "0",
    "team": "TBL",
    "toi": "16:44"
  },
  {
    "Date Pulled": "2017-03-24",
    "name": "Nelson Nogier",
    "points": "0",
    "team": "WPG",
    "toi": "13:12"
  },
  {
    "Date Pulled": "2017-03-24",
    "name": "Xavier Ouellet",
    "points": "0",
    "team": "DET",
    "toi": "16:48"
  },
  {
    "Date Pulled": "2017-03-24",
    "name": "Adam Pelech",
    "points": "0",
    "team": "NYI",
    "toi": "19:10"
  },
  {
    "Date Pulled": "2017-03-24",
    "name": "Nic Petan",
    "points": "0",
    "team": "WPG",
    "toi": "9:51"
  },
  {
    "Date Pulled": "2017-03-24",
    "name": "Rickard Rakell",
    "points": "0",
    "team": "ANA",
    "toi": "16:03"
  },
  {
    "Date Pulled": "2017-03-24",
    "name": "Robbie Russo",
    "points": "0",
    "team": "DET",
    "toi": "12:41"
  },
  {
    "Date Pulled": "2017-03-24",
    "name": "Patrick Sharp",
    "points": "0",
    "team": "DAL",
    "toi": "15:29"
  },
  {
    "Date Pulled": "2017-03-24",
    "name": "Devin Shore",
    "points": "0",
    "team": "DAL",
    "toi": "14:20"
  },
  {
    "Date Pulled": "2017-03-24",
    "name": "Mark Streit",
    "points": "0",
    "team": "PIT",
    "toi": "21:07"
  },
  {
    "Date Pulled": "2017-03-24",
    "name": "Mark Stuart",
    "points": "0",
    "team": "WPG",
    "toi": "14:11"
  },
  {
    "Date Pulled": "2017-03-24",
    "name": "Oskar Sundqvist",
    "points": "0",
    "team": "PIT",
    "toi": "9:36"
  },
  {
    "Date Pulled": "2017-03-24",
    "name": "Andrej Sustr",
    "points": "0",
    "team": "TBL",
    "toi": "17:19"
  },
  {
    "Date Pulled": "2017-03-24",
    "name": "Brandon Tanev",
    "points": "0",
    "team": "WPG",
    "toi": "10:56"
  },
  {
    "Date Pulled": "2017-03-24",
    "name": "Tomas Tatar",
    "points": "0",
    "team": "DET",
    "toi": "20:38"
  },
  {
    "Date Pulled": "2017-03-24",
    "name": "Nate Thompson",
    "points": "0",
    "team": "ANA",
    "toi": "10:35"
  },
  {
    "Date Pulled": "2017-03-24",
    "name": "Chris Thorburn",
    "points": "0",
    "team": "WPG",
    "toi": "7:20"
  },
  {
    "Date Pulled": "2017-03-24",
    "name": "Sami Vatanen",
    "points": "0",
    "team": "ANA",
    "toi": "21:50"
  },
  {
    "Date Pulled": "2017-03-24",
    "name": "Joel Vermin",
    "points": "0",
    "team": "TBL",
    "toi": "9:28"
  },
  {
    "Date Pulled": "2017-03-24",
    "name": "Marc-Edouard Vlasic",
    "points": "0",
    "team": "SJS",
    "toi": "14:46"
  },
  {
    "Date Pulled": "2017-03-24",
    "name": "Chris Wagner",
    "points": "0",
    "team": "ANA",
    "toi": "9:37"
  },
  {
    "Date Pulled": "2017-03-24",
    "name": "Luke Witkowski",
    "points": "0",
    "team": "TBL",
    "toi": "10:05"
  },
  {
    "Date Pulled": "2017-03-24",
    "name": "Joel Armia",
    "points": "0",
    "team": "WPG",
    "toi": "12:23"
  },
  {
    "Date Pulled": "2017-03-24",
    "name": "Andreas Athanasiou",
    "points": "0",
    "team": "DET",
    "toi": "11:29"
  },
  {
    "Date Pulled": "2017-03-24",
    "name": "Cal Clutterbuck",
    "points": "0",
    "team": "NYI",
    "toi": "13:48"
  },
  {
    "Date Pulled": "2017-03-24",
    "name": "Andrew Copp",
    "points": "0",
    "team": "WPG",
    "toi": "12:12"
  },
  {
    "Date Pulled": "2017-03-24",
    "name": "Brian Dumoulin",
    "points": "0",
    "team": "PIT",
    "toi": "21:58"
  },
  {
    "Date Pulled": "2017-03-24",
    "name": "Mike Green",
    "points": "0",
    "team": "DET",
    "toi": "23:41"
  },
  {
    "Date Pulled": "2017-03-24",
    "name": "Micheal Haley",
    "points": "0",
    "team": "SJS",
    "toi": "13:37"
  },
  {
    "Date Pulled": "2017-03-24",
    "name": "Thomas Hickey",
    "points": "0",
    "team": "NYI",
    "toi": "17:22"
  },
  {
    "Date Pulled": "2017-03-24",
    "name": "Andrew Ladd",
    "points": "0",
    "team": "NYI",
    "toi": "19:31"
  },
  {
    "Date Pulled": "2017-03-24",
    "name": "Bryan Little",
    "points": "0",
    "team": "WPG",
    "toi": "14:56"
  },
  {
    "Date Pulled": "2017-03-24",
    "name": "Adam Lowry",
    "points": "0",
    "team": "WPG",
    "toi": "16:02"
  },
  {
    "Date Pulled": "2017-03-24",
    "name": "Anthony Mantha",
    "points": "0",
    "team": "DET",
    "toi": "9:47"
  },
  {
    "Date Pulled": "2017-03-24",
    "name": "Patrick Marleau",
    "points": "0",
    "team": "SJS",
    "toi": "16:43"
  },
  {
    "Date Pulled": "2017-03-24",
    "name": "Julian Melchiori",
    "points": "0",
    "team": "WPG",
    "toi": "22:08"
  },
  {
    "Date Pulled": "2017-03-24",
    "name": "Justin Schultz",
    "points": "0",
    "team": "PIT",
    "toi": "24:45"
  },
  {
    "Date Pulled": "2017-03-24",
    "name": "Riley Sheahan",
    "points": "0",
    "team": "DET",
    "toi": "16:31"
  },
  {
    "Date Pulled": "2017-03-24",
    "name": "Marcus Sorensen",
    "points": "0",
    "team": "SJS",
    "toi": "14:03"
  },
  {
    "Date Pulled": "2017-03-24",
    "name": "Anton Stralman",
    "points": "0",
    "team": "TBL",
    "toi": "27:00"
  },
  {
    "Date Pulled": "2017-03-24",
    "name": "Jacob Trouba",
    "points": "0",
    "team": "WPG",
    "toi": "29:18"
  },
  {
    "Date Pulled": "2017-03-24",
    "name": "Joel Ward",
    "points": "0",
    "team": "SJS",
    "toi": "16:26"
  },
  {
    "Date Pulled": "2017-03-24",
    "name": "Anthony Beauvillier",
    "points": "0",
    "team": "NYI",
    "toi": "16:29"
  },
  {
    "Date Pulled": "2017-03-24",
    "name": "Mikkel Boedker",
    "points": "0",
    "team": "SJS",
    "toi": "14:27"
  },
  {
    "Date Pulled": "2017-03-24",
    "name": "Nick Bonino",
    "points": "0",
    "team": "PIT",
    "toi": "19:19"
  },
  {
    "Date Pulled": "2017-03-24",
    "name": "Brenden Dillon",
    "points": "0",
    "team": "SJS",
    "toi": "18:52"
  },
  {
    "Date Pulled": "2017-03-24",
    "name": "Joonas Donskoi",
    "points": "0",
    "team": "SJS",
    "toi": "14:08"
  },
  {
    "Date Pulled": "2017-03-24",
    "name": "Jannik Hansen",
    "points": "0",
    "team": "SJS",
    "toi": "14:38"
  },
  {
    "Date Pulled": "2017-03-24",
    "name": "Tomas Hertl",
    "points": "0",
    "team": "SJS",
    "toi": "15:39"
  },
  {
    "Date Pulled": "2017-03-24",
    "name": "Patric Hornqvist",
    "points": "0",
    "team": "PIT",
    "toi": "16:32"
  },
  {
    "Date Pulled": "2017-03-24",
    "name": "Chris Kunitz",
    "points": "0",
    "team": "PIT",
    "toi": "15:36"
  },
  {
    "Date Pulled": "2017-03-24",
    "name": "Joe Pavelski",
    "points": "0",
    "team": "SJS",
    "toi": "14:32"
  },
  {
    "Date Pulled": "2017-03-24",
    "name": "Mark Scheifele",
    "points": "0",
    "team": "WPG",
    "toi": "23:12"
  },
  {
    "Date Pulled": "2017-03-24",
    "name": "Brian Strait",
    "points": "0",
    "team": "WPG",
    "toi": "14:59"
  },
  {
    "Date Pulled": "2017-03-24",
    "name": "Paul Martin",
    "points": "0",
    "team": "SJS",
    "toi": "20:35"
  },
  {
    "Date Pulled": "2017-03-24",
    "name": "David Schlemko",
    "points": "0",
    "team": "SJS",
    "toi": "19:21"
  },
  {
    "Date Pulled": "2017-03-24",
    "name": "Chris Tierney",
    "points": "0",
    "team": "SJS",
    "toi": "14:05"
  }
]